{
    "id": "steamgame",
	"name": "Windows Game",
	"className": "SteamGameProgram",

	"requireInternet": true,
	"requireFullscreen": true,

	"pauseOptions": {
        "Toggle Steam Menu": "program.menu",
    },

    "pauseOrder": [
        "Toggle Steam Menu"
    ],

    "exe": [
        "20XX.exe",
        "30XX.exe",
		"AI.exe",
		"Bastion.exe",
		"ShippingPC-BmGame.exe",
		"BattleBlockTheater.exe",
		"Bayonetta.exe",
		"isaac-ng.exe",
		"BioshockHD.exe",
		"Bioshock2HD.exe",
		"BioshockInfinite.exe",
		"Borderlands2.exe",
		"braid.exe",
		"castle.exe",
		"Celeste.exe",
		"Clustertruck.exe",
		"Cuphead.exe",
		"DARKSOULS.exe",
		"DarkSoulsII.exe",
		"DarkSoulsIII.exe",
		"deadcells.exe",
		"Dishonored.exe",
		"Dishonored2.exe",
		"DOOMx64.exe",
		"DOOMx64vk.exe",
		"RED-Win64-Shipping.exe",
		"DuckGame.exe",
		"SkyrimSE.exe",
		"TheEndIsNigh.exe",
		"Fallout3.exe",
		"FalloutNV.exe",
		"Fallout4.exe",
		"ffxv_s.exe",
		"FortniteClient-Win64-Shipping.exe",
		"Furi.exe",
		"Gang Beasts.exe",
		"gta3.exe",
		"gta-vc.exe",
		"gta-sa.exe",
		"EFLC.exe",
		"GuiltyGearXrd.exe",
		"bms.exe",
		"hl2.exe",
		"eldorado.exe",
		"HatinTimeGame.exe",
		"HITMAN.exe",
		"hollow_knight.exe",
		"INSIDE.exe",
		"JustCause3.exe",
		"KingOfFighters98UM_x64.exe",
		"KingOfFighters2002UM_x64.exe",
		"left4dead2.exe",
		"LEGOStarWarsSaga.exe",
		"limbo.exe",
		"MadMax.exe",
		"game.exe",
		"mgsvtpp.exe",
		"mgsvmgo.exe",
		"ShadowOfMordor.exe",
		"MirrorsEdge.exe",
		"MonsterHunterWorld.exe",
		"MK10.exe",
		"MountYourFriends.exe",
		"NSUNS4.exe",
		"NFS11.exe",
		"Nidhogg.exe",
		"NieRAutomata.exe",
		"NBA2K19.exe",
		"NNT.exe",
		"oriDE.exe",
		"portal2.exe",
		"Psychonauts.exe",
		"bio4.exe",
		"re7.exe",
		"ROTTR.exe",
		"RivalsofAether.exe",
		"RocketLeague.exe",
		"SaintsRowIV.exe",
		"ShovelKnight.exe",
		"SkullGirls.exe",
		"SonicMania.exe",
		"Spelunky.exe",
		"Starwhal.exe",
		"StriderX64_r.exe",
		"SuperMeatBoy.exe",
		"SH.exe",
		"TekkenGame-Win64-Shipping.exe",
		"Transistor.exe",
		"SSFIV.exe",
		"VVVVVV.exe",
		"witcher3.exe",
		"WolfNewOrder_x64.exe",
		"Yakuza0.exe",
		"sdhdship.exe",
		"Overwatch.exe",
		"bf1.exe",
		"payday2_win32_release.exe",
		"CMW.exe",
		"METAL GEAR RISING REVENGEANCE.exe",
		"bhd.exe",
		"Ninja.exe",
		"This War of Mine.exe",
		"Wreckfest_x64.exe",
		"dontstarve_steam.exe",
		"IamBread.exe",
		"WizardOfLegend.exe",
		"Overcooked2.exe",
		"DevilMayCry5.exe",
		"EtG.exe",
		"SoulcaliburVI.exe",
		"re2.exe",
		"HotlineGL.exe",
		"ApeOut.exe",
		"Katana ZERO.exe",
		"Baba Is You.exe",
		"drt.exe",
		"CrashBandicootNSaneTrilogy.exe",
		"Spyro-Win64-Shipping.exe",
		"HorizonChase.exe",
		"YLILWin64.exe",
		"SpeedRunners.exe",
		"SonicGenerations.exe",
		"I Wanna Be The Boshy.exe",
		"TombRaider.exe",
		"umvc3.exe",
		"Worms W.M.D.exe",
		"mbacPC.exe",
		"sw.x64.exe",
		"MassEffect.exe",
		"MassEffect2.exe",
		"SaintsRowTheThird_DX11.exe",
		"wargroove64.exe",
		"soniccd.exe",
		"Golf With Your Friends.exe",
		"BatmanAC.exe",
		"Injustice.exe",
		"CaveStory+.exe",
		"HyperLightDrifter.exe",
		"Outward.exe",
		"KillerInstinctX64_r.exe",
		"Timespinner.exe",
		"SHMCD.exe",
		"Final Fight LNS Ultimate.exe",
		"Oblivion.exe",
		"srb2kart.exe",
		"srb2win.exe",
		"Spel2.exe",
		"LEGOLCUR_DX11.exe",
		"LittleNightmares.exe",
		"GGXXACPR_Win.exe",
		"BloodstainedRotN-Win64-Shipping.exe",
		"sonic.exe",
		"sonic2app.exe",
		"sunset.exe",
		"My Friend Pedro - Blood Bullets Bananas.exe",
		"Stardew Valley.exe",
		"FEZ.exe",
		"Hades.exe",
		"HotshotRacing.exe",
		"WHAT THE GOLF.exe",
		"oriwotw.exe",
		"MaxPayne.exe",
		"maxpayne2.exe",
		"witcher2.exe",
		"Fable Anniversary.exe",
		"Shenmue.exe",
		"Shenmue2.exe",
		"Tsonic_win.exe",
		"OuterWilds.exe",
		"AlanWake.exe",
		"Control_DX11.exe",
		"Control_DX12.exe",
		"Ghostrunner-Win64-Shipping.exe",
		"Sonic.exe",
		"Sonic 2.exe",
		"GGST-Win64-Shipping.exe",
		"AxiomVerge.exe",
		"Cursed_Castilla.exe",
		"DragonsLair.exe",
		"FP.exe",
		"Guac2_x64.exe",
		"sekiro.exe",
		"dmc1.exe",
		"dmc2.exe",
		"dmc3.exe",
		"dmcLauncher.exe",
		"DevilMayCry4SpecialEdition.exe",
		"UNDERTALE.exe",
		"PuyoPuyoTetris2.exe",
		"SOR4.exe",
		"ASN_App_PcDx9_Final.exe",
		"SuperliminalSteam.exe",
		"Adventures of Chris.exe",
		"DH-Win64-Shipping.exe",
		"Vanquish.exe",
		"Nickelodeon All-Star Brawl.exe",
		"RSDKv4_64_rev02.exe",
		"Tsonic_win.exe",
		"Rayman Origins.exe",
		"Rayman Legends.exe",
		"TheWonderful101.exe",
		"ds.exe",
		"EDF5.exe",
		"PROA34-Win64-Shipping.exe",
		"DOOMEternalx64vk.exe",
		"MultiVersus-Win64-Shipping.exe",
		"Yoku.exe",
		"GeometryWars.exe",
		"RDR2.exe",
		"Bug Fables.exe",
		"Super Sami Roll.exe",
        "The Jackbox Party Pack.exe",
        "The Jackbox Party Pack 2.exe",
        "The Jackbox Party Pack 3.exe",
        "YakuzaKiwami.exe",
        "YakuzaKiwami2.exe",
        "Yakuza3.exe",
        "Yakuza4.exe",
        "Yakuza5.exe",
        "Yakuza6.exe",
		"NinoKuni_WotWW_Remastered.exe",
		"Nino2.exe",
		"Psychonauts2-Win64-Shipping.exe",
        "YakuzaLikeADragon.exe",
        "EXO ONE.exe",
		"noita.exe",
		"FightCrab.exe",
		"re3.exe",
		"re5dx9.exe",
		"Journey.exe",
		"LEGOSTARWARSSKYWALKERSAGA_DX11.exe",
		"Demon Turf.exe",
		"Demon Turf TOWER.exe",
		"Broforce_beta.exe",
		"HotlineMiami2.exe",
		"TheMessenger.exe",
		"Catherine.exe",
		"Sifu-Win64-Shipping.exe",
		"The Stanley Parable Ultra Deluxe.exe",
		"PAC-MAN.exe",
		"GoW.exe",
		"Spider-Man.exe",
		"MilesMorales.exe",
		"u4.exe",
		"RUNNER.exe",
		"NieR Replicant ver.1.22474487139.exe",
		"TowerFall.exe",
		"VampireSurvivors.exe",
		"cannonball.exe",
		"FF8_EN.exe",
		"FF9.exe",
		"FFX&X-2_LAUNCHER.exe",
		"FFX&X-2_Will.exe",
		"FFX.exe",
		"FFX-2.exe",
		"SonicR.exe",
		"Launcher Nickelodeon All-Star Brawl.exe",
		"Subnautica.exe",
		"SubnauticaZero.exe",
		"THPS12.exe",
		"Windjammers2.exe",
		"HITMAN3.exe",
		"sh3.exe",
		"BH6.exe",
		"SonicFrontiers.exe",
		"katamari.exe",
		"WLKRR.exe",
		"BatmanOrigins.exe",
		"FlightSimulator.exe",
		"BatmanAK.exe",
		"makaimura_GG_RE.exe",
		"Pineapple-Win64-Shipping.exe",
		"Risk of Rain 2.exe",
		"Palworld-Win64-Shipping.exe"
    ],

	"overrides": {
		; Batman Arkham Asylum
		"\/200260([^0-9]|$)": "BatmanArkhamProgram",
		; BatMan Arkham City
        "\/35140([^0-9]|$)": "BatmanArkhamProgram",
		; Skyrim SE
        "\/489830([^0-9]|$)": "SkyrimSEProgram",
		; Fallout 3
        "\/22370([^0-9]|$)": "Fallout3Program",
		; Fallout New Vegas
        "\/22380([^0-9]|$)": "FalloutNVProgram",
		; Fallout 4
        "\/377160([^0-9]|$)": "Fallout4Program",
		; HITMAN
        "\/236870([^0-9]|$)": "HitmanProgram",
		; HITMAN 3
        "\/1659040([^0-9]|$)": "Hitman3Program",
		; Saints Row 3 
        "\/55230([^0-9]|$)": "SaintsRow3Program",
		; Witcher 2
        "\/20920([^0-9]|$)": "Witcher2Program",
		; Witcher 3
		"\/292030([^0-9]|$)": "Witcher3Program",
		; Oblivion
        "\/22330([^0-9]|$)": "OblivionProgram",
		; Hotline Miami
        "\/219150([^0-9]|$)": "HotlineMiamiProgram",
		; SUPERHOT
        "\/322500([^0-9]|$)": "SuperHotProgram",
		; SUPERHOT 2
        "\/690040([^0-9]|$)": "SuperHot2Program",
		; Red Dead Redemption 2
        "\/1174180([^0-9]|$)": "RDR2Program",
		; Shenmue 1 & 2
        "\/758330([^0-9]|$)": "ShenmueProgram",
		; Spider-Man
		"\/1817070([^0-9]|$)": "SpiderManProgram",
		; Spider-Man Miles Morales
		"\/1817190([^0-9]|$)": "SpiderManProgram",
		; Dark Souls III
        "\/374320([^0-9]|$)": "DarkSouls3Program",
		; BioShock HD
		"\/409710([^0-9]|$)": "BioShockHDProgram",
		; BioShock 2 HD
		"\/409720([^0-9]|$)": "BioShockHDProgram",
		; Clustertruck
		"\/397950([^0-9]|$)": "ClustertruckProgram",
		; Blue Fire
		"\/1220150([^0-9]|$)": "BlueFireProgram",
		; Braid
		"\/26800([^0-9]|$)": "BraidProgram",
		; Undertale
		"\/391540([^0-9]|$)": "UndertaleProgram",
		; OutRun
		"\/17526394833466294272([^0-9]|$)": "CannonballProgram",
		; Final Fantasy 8
		"\/39150([^0-9]|$)": "FF8Program",
		; Final Fantasy 9
		"\/377840([^0-9]|$)": "FF9Program",
		; Microsoft Flight Simulator
		"\/1250410([^0-9]|$)": "MicrosoftFlightSimProgram",
		; Bastion
        "\/107100([^0-9]|$)": {
			"defaultArgs": "-x 3840 -y 2160",
			"requireFullscreen": false
		},
		; Grand Theft Auto III
        "\/12100([^0-9]|$)": {
			"defaultArgs": "-skip"
		},
		; Grand Theft Auto Vice City
        "\/12110([^0-9]|$)": {
			"defaultArgs": "-skip"
		},
		; Grand Theft Auto San Andreas
        "\/12120([^0-9]|$)": {
			"defaultArgs": "-skip"
		},
		; Tomb Raider 2013
        "\/203160([^0-9]|$)": {
			"defaultArgs": "-nolauncher"
		},
		; Rise of the Tomb Raider
        "\/391220([^0-9]|$)": {
			"defaultArgs": "-nolauncher"
		},
		; Control
        "\/870780([^0-9]|$)": {
			"defaultArgs": "-dx12"
		},
		; Sonic Adventure 2 Battle
        "\/213610([^0-9]|$)": {
			"defaultArgs": "-q"
		},
		; Max Payne
		"\/12140([^0-9]|$)": {
			"defaultArgs": "-nodialog -skipstartup",
			"mouse": {
				"initialPos": [0.5, 0.5]
			}
		},
		; Max Payne 2
		"\/12150([^0-9]|$)": {
			"defaultArgs": "-nodialog -skipstartup",
			"mouse": {
				"initialPos": [0.5, 0.5]
			}
		},
		; Portal
		"\/400([^0-9]|$)": {
			"defaultArgs": "-gamepadui",
			"mouse": {
				"initialPos": [0.5, 0.5]
			}
		}, 
		; Half-Life 2
		"\/220([^0-9]|$)": {
			"defaultArgs": "-gamepadui",
			"mouse": {
				"initialPos": [0.5, 0.5]
			}
		},
	}
}